autoxx/agent/babyagi/agi.py
autoxx/agent/babyagi/task_manager.py
autoxx/agent/react/agent.py
autoxx/config/config.py
autoxx/setup.py
autoxx/tools/knowledge_base/app.py
autoxx/tools/knowledge_base/base.py
autoxx/tools/knowledge_base/prompts/__init__.py
autoxx/tools/knowledge_base/prompts/qa
autoxx/tools/llm/base.py
autoxx/tools/web_search/js/overlay.js
autoxx/tools/web_search/search.py
autoxx/utils/base.py
autoxx/utils/llm.py
autoxx/utils/openai_models.py
autoxx/utils/processing_html.py
autoxx/utils/processing_text.py
autoxx/utils/token_counter.py
autoxx-0.0.40.dist-info/METADATA
autoxx-0.0.40.dist-info/WHEEL
autoxx-0.0.40.dist-info/RECORD
