Metadata-Version: 2.1
Name: autoxx
Version: 0.0.40
Summary: LLM-based autonomous agent
License: MIT
Author: IANTHEREAL
Author-email: argregoryian@gmail.com
Requires-Python: >=3.10,<4.0
Classifier: License :: OSI Approved :: MIT License
Classifier: Programming Language :: Python :: 3
Classifier: Programming Language :: Python :: 3.10
Classifier: Programming Language :: Python :: 3.11
Requires-Dist: bs4 (==0.0.1)
Requires-Dist: colorama (>=0.4.6,<0.5.0)
Requires-Dist: gTTS (==2.3.1)
Requires-Dist: google-api-python-client (>=2.86.0,<3.0.0)
Requires-Dist: langchain (>=0.0.218,<0.0.219)
Requires-Dist: llama-index (==0.6.27)
Requires-Dist: openai (>=0.27.8,<0.28.0)
Requires-Dist: orjson (==3.8.10)
Requires-Dist: pinecone-client (==2.2.1)
Requires-Dist: playsound (==1.2.2)
Requires-Dist: pymongo (>=4.3.3,<5.0.0)
Requires-Dist: python-dotenv (==1.0.0)
Requires-Dist: selenium (==4.9.0)
Requires-Dist: spacy (>=3.0.0,<4.0.0)
Requires-Dist: tiktoken (==0.3.3)
Requires-Dist: transformers (>=4.30.1,<5.0.0)
Requires-Dist: webdriver_manager (==3.8.6)
